Metadata-Version: 2.1
Name: textlist
Version: 1.0.0
Summary: 插入不同的字符、字体
Home-page: https://github.com/
Author: Jianrui Li
Author-email: lijianrui7560@qq.com
License: UNKNOWN
Platform: UNKNOWN
Classifier: Programming Language :: Python :: 3
Classifier: License :: OSI Approved :: MIT License
Classifier: Operating System :: OS Independent
